pyusers/__init__.py
pyusers-0.0.1.dist-info/WHEEL
pyusers-0.0.1.dist-info/METADATA
pyusers-0.0.1.dist-info/RECORD
